test_poetrino/__init__.py
test_poetrino/main.py
test_poetrino-0.1.8.dist-info/WHEEL
test_poetrino-0.1.8.dist-info/METADATA
test_poetrino-0.1.8.dist-info/RECORD
