Metadata-Version: 2.1
Name: test-poetrino
Version: 0.1.8
Summary: 
Author: Sasen Perera
Author-email: sasen.learnings@gmail.com
Requires-Python: >=3.10,<4.0
Classifier: Programming Language :: Python :: 3
Classifier: Programming Language :: Python :: 3.10
Requires-Dist: blessed (>=1.19.1,<2.0.0)
